tark/__init__.py
tark/parser.py
tark/states.py
tark/structures.py
tark/tark.py
tark/tokenizer.py
tark/states/__init__.py
tark/states/codeblock.py
tark/states/image.py
tark/states/inlinecode.py
tark/states/link.py
tark/states/plain.py
tark/states/text.py
tark/states/tick.py
tark/states/title.py
tark-0.0.4.dist-info/LICENSE
tark-0.0.4.dist-info/METADATA
tark-0.0.4.dist-info/WHEEL
tark-0.0.4.dist-info/top_level.txt
tark-0.0.4.dist-info/RECORD
